klickbrick_mb.py
klickbrick_mb-0.1.0.dist-info/entry_points.txt
klickbrick_mb-0.1.0.dist-info/LICENSE
klickbrick_mb-0.1.0.dist-info/WHEEL
klickbrick_mb-0.1.0.dist-info/METADATA
klickbrick_mb-0.1.0.dist-info/RECORD
