Metadata-Version: 2.1
Name: klickbrick-mb
Version: 0.1.0
Summary: An Extensible Python CLI
License: MIT
Author: Matthias Busch
Author-email: dev.mbusch@gmail.com
Requires-Python: >=3.8,<4.0
Classifier: License :: OSI Approved :: MIT License
Classifier: Programming Language :: Python :: 3
Classifier: Programming Language :: Python :: 3.8
Classifier: Programming Language :: Python :: 3.9
